Workbook

Sheet Merge Plan
A1: SaaS Merge - Execution Plan
A2: Window: Tue 8 Sep 2026 to Thu 1 Oct 2026 | 18 working days | Yellow cells with blue text are yours to edit
A4: ID | B4: Milestone | C4: Task | D4: Owner | E4: Start | F4: End | G4: Work Days | H4: Depends On | I4: Status | J4: % Done | K4: Critical Path | L4: Notes / Exit Criteria
A5: 0.1 | B5: M0. Program Setup | C5: Name single decision owner and escalation path | D5: Exec Sponsor | E5: 46273 | F5: 46273 | G5: =NETWORKDAYS(E5,F5) -> 1 | I5: Not Started | J5: 0 | K5: Y | L5: One named person can break ties without a committee
A6: 0.2 | B6: M0. Program Setup | C6: Stand up shared tracker, comms channel and daily 15-min standup | D6: PM | E6: 46273 | F6: 46273 | G6: =NETWORKDAYS(E6,F6) -> 1 | H6: 0.1 | I6: Not Started | J6: 0 | K6: Y | L6: Both teams working from one board, not two
A7: 0.3 | B7: M0. Program Setup | C7: Agree what 'done by 1 Oct' means vs what slips to Q4 | D7: Exec Sponsor / PM | E7: 46273 | F7: 46274 | G7: =NETWORKDAYS(E7,F7) -> 2 | H7: 0.1 | I7: Not Started | J7: 0 | K7: Y | L7: Written scope statement signed by both product owners
A8: 0.4 | B8: M0. Program Setup | C8: Declare feature freeze and change-freeze windows | D8: Eng Leads | E8: 46274 | F8: 46274 | G8: =NETWORKDAYS(E8,F8) -> 1 | H8: 0.3 | I8: Not Started | J8: 0 | K8: Y | L8: No non-merge releases to either system during cutover week
A9: 0.5 | B9: M0. Program Setup | C9: Open RAID log (risks, assumptions, issues, dependencies) | D9: PM | E9: 46274 | F9: 46274 | G9: =NETWORKDAYS(E9,F9) -> 1 | H9: 0.2 | I9: Not Started | J9: 0 | K9: N | L9: Log live and reviewed at every standup
A10: 1.1 | B10: M1. Discovery & Inventory | C10: Inventory System A: services, repos, infra, runtimes, versions | D10: Eng Lead A | E10: 46273 | F10: 46275 | G10: =NETWORKDAYS(E10,F10) -> 3 | H10: 0.2 | I10: Not Started | J10: 0 | K10: Y | L10: Single source-of-truth inventory sheet
A11: 1.2 | B11: M1. Discovery & Inventory | C11: Inventory System B: services, repos, infra, runtimes, versions | D11: Eng Lead B | E11: 46273 | F11: 46275 | G11: =NETWORKDAYS(E11,F11) -> 3 | H11: 0.2 | I11: Not Started | J11: 0 | K11: Y | L11: Single source-of-truth inventory sheet
A12: 1.3 | B12: M1. Discovery & Inventory | C12: Export both data models / ERDs plus row counts per entity | D12: Data Lead | E12: 46273 | F12: 46275 | G12: =NETWORKDAYS(E12,F12) -> 3 | I12: Not Started | J12: 0 | K12: Y | L12: Entity list with volumes; feeds migration sizing
A13: 1.4 | B13: M1. Discovery & Inventory | C13: List all auth methods, IdPs, token and session mechanisms | D13: Security Lead | E13: 46274 | F13: 46275 | G13: =NETWORKDAYS(E13,F13) -> 2 | I13: Not Started | J13: 0 | K13: Y | L13: Needed before any identity decision
A14: 1.5 | B14: M1. Discovery & Inventory | C14: Catalog public APIs, webhooks, SDKs and their active consumers | D14: API Owner | E14: 46274 | F14: 46276 | G14: =NETWORKDAYS(E14,F14) -> 3 | I14: Not Started | J14: 0 | K14: Y | L14: Include call volumes per endpoint to rank what must survive
A15: 1.6 | B15: M1. Discovery & Inventory | C15: Catalog third-party integrations, vendors, licences, renewal dates | D15: Ops / Procurement | E15: 46274 | F15: 46276 | G15: =NETWORKDAYS(E15,F15) -> 3 | I15: Not Started | J15: 0 | K15: N | L15: Renewal dates drive the decommission notice periods
A16: 1.7 | B16: M1. Discovery & Inventory | C16: Map customer and tenant overlap (accounts present on both systems) | D16: CS Lead | E16: 46274 | F16: 46276 | G16: =NETWORKDAYS(E16,F16) -> 3 | H16: 1.3 | I16: Not Started | J16: 0 | K16: Y | L16: Overlap list drives dedup rules and pilot selection
A17: 1.8 | B17: M1. Discovery & Inventory | C17: Compile compliance obligations: SOC 2, ISO, GDPR, data residency | D17: Compliance | E17: 46275 | F17: 46276 | G17: =NETWORKDAYS(E17,F17) -> 2 | I17: Not Started | J17: 0 | K17: Y | L17: Merged system is a new audit boundary
A18: 1.9 | B18: M1. Discovery & Inventory | C18: Write gap and overlap analysis; hold review session | D18: PM / Eng Leads | E18: 46276 | F18: 46276 | G18: =NETWORKDAYS(E18,F18) -> 1 | H18: 1.1 | I18: Not Started | J18: 0 | K18: Y | L18: GATE: discovery signed off before architecture decision
A19: 1b.1 | B19: M1b. Defect Triage & Data Integrity | C19: Pull the full defect backlog from the broken system and de-duplicate it | D19: Eng Lead (broken sys) | E19: 46274 | F19: 46275 | G19: =NETWORKDAYS(E19,F19) -> 2 | H19: 0.2 | I19: Not Started | J19: 0 | K19: Y | L19: Include unlogged known issues; ask support, not just the tracker
A20: 1b.2 | B20: M1b. Defect Triage & Data Integrity | C20: Confirm WHICH system is broken: the surviving one or the retiring one | D20: Exec Sponsor / Architect | E20: 46274 | F20: 46274 | G20: =NETWORKDAYS(E20,F20) -> 1 | H20: 1b.1 | I20: Not Started | J20: 0 | K20: Y | L20: GATE: if the SURVIVING system is the broken one, stop and re-plan - see Legend tab
A21: 1b.3 | B21: M1b. Defect Triage & Data Integrity | C21: Classify every defect: data-corrupting / behavioural / cosmetic | D21: Eng Lead + Data Lead | E21: 46275 | F21: 46279 | G21: =NETWORKDAYS(E21,F21) -> 3 | H21: 1b.1 | I21: Not Started | J21: 0 | K21: Y | L21: Only the data-corrupting class threatens the merge
A22: 1b.4 | B22: M1b. Defect Triage & Data Integrity | C22: Quantify the corruption blast radius: which entities, how many records | D22: Data Lead | E22: 46276 | F22: 46281 | G22: =NETWORKDAYS(E22,F22) -> 4 | H22: 1b.3 | I22: Not Started | J22: 0 | K22: Y | L22: Record counts per defect; this sizes the cleansing effort
A23: 1b.5 | B23: M1b. Defect Triage & Data Integrity | C23: Decide fix vs retire per defect and freeze everything else | D23: Exec Sponsor / Eng Lead | E23: 46280 | F23: 46280 | G23: =NETWORKDAYS(E23,F23) -> 1 | H23: 1b.4 | I23: Not Started | J23: 0 | K23: Y | L23: GATE: do NOT fix bugs in a system you are retiring unless they corrupt migrating data
A24: 1b.6 | B24: M1b. Defect Triage & Data Integrity | C24: Run data-quality profiling: nulls, orphans, duplicates, broken FKs, out-of-range values | D24: Data Lead | E24: 46276 | F24: 46282 | G24: =NETWORKDAYS(E24,F24) -> 5 | H24: 1.3 | I24: Not Started | J24: 0 | K24: Y | L24: Must finish BEFORE the ETL mapping spec is frozen (4.1)
A25: 1b.7 | B25: M1b. Defect Triage & Data Integrity | C25: Fix only the data-corrupting defects; everything else stays broken | D25: Eng Team | E25: 46281 | F25: 46288 | G25: =NETWORKDAYS(E25,F25) -> 6 | H25: 1b.5 | I25: Not Started | J25: 0 | K25: Y | L25: Stops the bleeding so migrated data does not keep degrading
A26: 1b.8 | B26: M1b. Defect Triage & Data Integrity | C26: Write cleansing and quarantine rules for records that cannot be repaired | D26: Data Lead | E26: 46282 | F26: 46288 | G26: =NETWORKDAYS(E26,F26) -> 5 | H26: 1b.6 | I26: Not Started | J26: 0 | K26: Y | L26: Three buckets: repair, quarantine, leave behind
A27: 1b.9 | B27: M1b. Defect Triage & Data Integrity | C27: Decide the policy for known-bad records: migrate, quarantine, or abandon | D27: Exec Sponsor / Legal | E27: 46286 | F27: 46288 | G27: =NETWORKDAYS(E27,F27) -> 3 | H27: 1b.8 | I27: Not Started | J27: 0 | K27: Y | L27: Customer-visible; may need contractual or regulatory input
A28: 1b.10 | B28: M1b. Defect Triage & Data Integrity | C28: Stabilisation gate: error rate flat for 3 consecutive days before dry runs | D28: Eng Lead | E28: 46288 | F28: 46289 | G28: =NETWORKDAYS(E28,F28) -> 2 | H28: 1b.7 | I28: Not Started | J28: 0 | K28: Y | L28: GATE: migrating off a still-degrading system invalidates every dry run
A29: 2.0 | B29: M2. Target Architecture Decision | C29: Re-weight the architecture options against the defect profile | D29: Architect | E29: 46279 | F29: 46279 | G29: =NETWORKDAYS(E29,F29) -> 1 | H29: 1b.3 | I29: Not Started | J29: 0 | K29: Y | L29: A badly broken system is a strong argument for absorb-and-retire over unify
... A87: 10.4 | B87: M10. Decommission (planning only by 1 Oct) | C87: Roadmap the out-of-scope items deferred past 1 Oct | D87: PM | E87: 46296 | F87: 46296 | G87: =NETWORKDAYS(E87,F87) -> 1 | H87: 2.4 | I87: Not Started | J87: 0 | K87: Y | L87: Closes the loop on the scope list from 2.4

Sheet Milestone Summary
A1: Milestone Rollup & Programme Status
A2: Every figure below is a formula reading the 'Merge Plan' tab. Update the plan, not this sheet.
A4: Deadline | B4: 46296
A5: Working days remaining (from today's date) | B5: =NETWORKDAYS(TODAY(),$B$4) -> 18
A6: Total tasks | B6: =COUNTA('Merge Plan'!$A$5:$A$87) -> 83
A7: Tasks complete | B7: =COUNTIF('Merge Plan'!$I$5:$I$87,"Done") -> 0
A8: Tasks blocked | B8: =COUNTIF('Merge Plan'!$I$5:$I$87,"Blocked") -> 0
A9: Overall % complete | B9: =IFERROR(AVERAGE('Merge Plan'!$J$5:$J$87),0) -> 0
A10: Critical-path tasks still open | B10: =COUNTIFS('Merge Plan'!$K$5:$K$87,"Y",'Merge Plan'!$I$5:$I$87,"<>Done") -> 71
A12: Milestone | B12: Tasks | C12: Done | D12: Blocked | E12: Start | F12: Finish | G12: % Complete | H12: Status
A13: M0. Program Setup | B13: =COUNTIF('Merge Plan'!$B$5:$B$87,$A13) -> 5 | C13: =COUNTIFS('Merge Plan'!$B$5:$B$87,$A13,'Merge Plan'!$I$5:$I$87,"Done") -> 0 | D13: =COUNTIFS('Merge Plan'!$B$5:$B$87,$A13,'Merge Plan'!$I$5:$I$87,"Blocked") -> 0 | E13: =_xlfn.MINIFS('Merge Plan'!$E$5:$E$87,'Merge Plan'!$B$5:$B$87,$A13) -> 46273 | F13: =_xlfn.MAXIFS('Merge Plan'!$F$5:$F$87,'Merge Plan'!$B$5:$B$87,$A13) -> 46274 | G13: =IFERROR(AVERAGEIF('Merge Plan'!$B$5:$B$87,$A13,'Merge Plan'!$J$5:$J$87),0) -> 0 | H13: =IF($D13>0,"Blocked",IF($C13=$B13,"Done",IF($C13>0,"In Progress","Not Started"))) -> Not Started
A14: M1. Discovery & Inventory | B14: =COUNTIF('Merge Plan'!$B$5:$B$87,$A14) -> 9 | C14: =COUNTIFS('Merge Plan'!$B$5:$B$87,$A14,'Merge Plan'!$I$5:$I$87,"Done") -> 0 | D14: =COUNTIFS('Merge Plan'!$B$5:$B$87,$A14,'Merge Plan'!$I$5:$I$87,"Blocked") -> 0 | E14: =_xlfn.MINIFS('Merge Plan'!$E$5:$E$87,'Merge Plan'!$B$5:$B$87,$A14) -> 46273 | F14: =_xlfn.MAXIFS('Merge Plan'!$F$5:$F$87,'Merge Plan'!$B$5:$B$87,$A14) -> 46276 | G14: =IFERROR(AVERAGEIF('Merge Plan'!$B$5:$B$87,$A14,'Merge Plan'!$J$5:$J$87),0) -> 0 | H14: =IF($D14>0,"Blocked",IF($C14=$B14,"Done",IF($C14>0,"In Progress","Not Started"))) -> Not Started
A15: M1b. Defect Triage & Data Integrity | B15: =COUNTIF('Merge Plan'!$B$5:$B$87,$A15) -> 10 | C15: =COUNTIFS('Merge Plan'!$B$5:$B$87,$A15,'Merge Plan'!$I$5:$I$87,"Done") -> 0 | D15: =COUNTIFS('Merge Plan'!$B$5:$B$87,$A15,'Merge Plan'!$I$5:$I$87,"Blocked") -> 0 | E15: =_xlfn.MINIFS('Merge Plan'!$E$5:$E$87,'Merge Plan'!$B$5:$B$87,$A15) -> 46274 | F15: =_xlfn.MAXIFS('Merge Plan'!$F$5:$F$87,'Merge Plan'!$B$5:$B$87,$A15) -> 46289 | G15: =IFERROR(AVERAGEIF('Merge Plan'!$B$5:$B$87,$A15,'Merge Plan'!$J$5:$J$87),0) -> 0 | H15: =IF($D15>0,"Blocked",IF($C15=$B15,"Done",IF($C15>0,"In Progress","Not Started"))) -> Not Started
A16: M2. Target Architecture Decision | B16: =COUNTIF('Merge Plan'!$B$5:$B$87,$A16) -> 6 | C16: =COUNTIFS('Merge Plan'!$B$5:$B$87,$A16,'Merge Plan'!$I$5:$I$87,"Done") -> 0 | D16: =COUNTIFS('Merge Plan'!$B$5:$B$87,$A16,'Merge Plan'!$I$5:$I$87,"Blocked") -> 0 | E16: =_xlfn.MINIFS('Merge Plan'!$E$5:$E$87,'Merge Plan'!$B$5:$B$87,$A16) -> 46275 | F16: =_xlfn.MAXIFS('Merge Plan'!$F$5:$F$87,'Merge Plan'!$B$5:$B$87,$A16) -> 46279 | G16: =IFERROR(AVERAGEIF('Merge Plan'!$B$5:$B$87,$A16,'Merge Plan'!$J$5:$J$87),0) -> 0 | H16: =IF($D16>0,"Blocked",IF($C16=$B16,"Done",IF($C16>0,"In Progress","Not Started"))) -> Not Started
A17: M3. Identity & Access Unification | B17: =COUNTIF('Merge Plan'!$B$5:$B$87,$A17) -> 7 | C17: =COUNTIFS('Merge Plan'!$B$5:$B$87,$A17,'Merge Plan'!$I$5:$I$87,"Done") -> 0 | D17: =COUNTIFS('Merge Plan'!$B$5:$B$87,$A17,'Merge Plan'!$I$5:$I$87,"Blocked") -> 0 | E17: =_xlfn.MINIFS('Merge Plan'!$E$5:$E$87,'Merge Plan'!$B$5:$B$87,$A17) -> 46280 | F17: =_xlfn.MAXIFS('Merge Plan'!$F$5:$F$87,'Merge Plan'!$B$5:$B$87,$A17) -> 46289 | G17: =IFERROR(AVERAGEIF('Merge Plan'!$B$5:$B$87,$A17,'Merge Plan'!$J$5:$J$87),0) -> 0 | H17: =IF($D17>0,"Blocked",IF($C17=$B17,"Done",IF($C17>0,"In Progress","Not Started"))) -> Not Started
A18: M4. Data Model Mapping & Migration | B18: =COUNTIF('Merge Plan'!$B$5:$B$87,$A18) -> 10 | C18: =COUNTIFS('Merge Plan'!$B$5:$B$87,$A18,'Merge Plan'!$I$5:$I$87,"Done") -> 0 | D18: =COUNTIFS('Merge Plan'!$B$5:$B$87,$A18,'Merge Plan'!$I$5:$I$87,"Blocked") -> 0 | E18: =_xlfn.MINIFS('Merge Plan'!$E$5:$E$87,'Merge Plan'!$B$5:$B$87,$A18) -> 46280 | F18: =_xlfn.MAXIFS('Merge Plan'!$F$5:$F$87,'Merge Plan'!$B$5:$B$87,$A18) -> 46295 | G18: =IFERROR(AVERAGEIF('Merge Plan'!$B$5:$B$87,$A18,'Merge Plan'!$J$5:$J$87),0) -> 0 | H18: =IF($D18>0,"Blocked",IF($C18=$B18,"Done",IF($C18>0,"In Progress","Not Started"))) -> Not Started
A19: M5. Billing & Subscription Consolidation | B19: =COUNTIF('Merge Plan'!$B$5:$B$87,$A19) -> 7 | C19: =COUNTIFS('Merge Plan'!$B$5:$B$87,$A19,'Merge Plan'!$I$5:$I$87,"Done") -> 0 | D19: =COUNTIFS('Merge Plan'!$B$5:$B$87,$A19,'Merge Plan'!$I$5:$I$87,"Blocked") -> 0 | E19: =_xlfn.MINIFS('Merge Plan'!$E$5:$E$87,'Merge Plan'!$B$5:$B$87,$A19) -> 46280 | F19: =_xlfn.MAXIFS('Merge Plan'!$F$5:$F$87,'Merge Plan'!$B$5:$B$87,$A19) -> 46295 | G19: =IFERROR(AVERAGEIF('Merge Plan'!$B$5:$B$87,$A19,'Merge Plan'!$J$5:$J$87),0) -> 0 | H19: =IF($D19>0,"Blocked",IF($C19=$B19,"Done",IF($C19>0,"In Progress","Not Started"))) -> Not Started
A20: M6. API & Integration Compatibility | B20: =COUNTIF('Merge Plan'!$B$5:$B$87,$A20) -> 6 | C20: =COUNTIFS('Merge Plan'!$B$5:$B$87,$A20,'Merge Plan'!$I$5:$I$87,"Done") -> 0 | D20: =COUNTIFS('Merge Plan'!$B$5:$B$87,$A20,'Merge Plan'!$I$5:$I$87,"Blocked") -> 0 | E20: =_xlfn.MINIFS('Merge Plan'!$E$5:$E$87,'Merge Plan'!$B$5:$B$87,$A20) -> 46281 | F20: =_xlfn.MAXIFS('Merge Plan'!$F$5:$F$87,'Merge Plan'!$B$5:$B$87,$A20) -> 46294 | G20: =IFERROR(AVERAGEIF('Merge Plan'!$B$5:$B$87,$A20,'Merge Plan'!$J$5:$J$87),0) -> 0 | H20: =IF($D20>0,"Blocked",IF($C20=$B20,"Done",IF($C20>0,"In Progress","Not Started"))) -> Not Started
A21: M7. Unified Experience | B21: =COUNTIF('Merge Plan'!$B$5:$B$87,$A21) -> 6 | C21: =COUNTIFS('Merge Plan'!$B$5:$B$87,$A21,'Merge Plan'!$I$5:$I$87,"Done") -> 0 | D21: =COUNTIFS('Merge Plan'!$B$5:$B$87,$A21,'Merge Plan'!$I$5:$I$87,"Blocked") -> 0 | E21: =_xlfn.MINIFS('Merge Plan'!$E$5:$E$87,'Merge Plan'!$B$5:$B$87,$A21) -> 46282 | F21: =_xlfn.MAXIFS('Merge Plan'!$F$5:$F$87,'Merge Plan'!$B$5:$B$87,$A21) -> 46295 | G21: =IFERROR(AVERAGEIF('Merge Plan'!$B$5:$B$87,$A21,'Merge Plan'!$J$5:$J$87),0) -> 0 | H21: =IF($D21>0,"Blocked",IF($C21=$B21,"Done",IF($C21>0,"In Progress","Not Started"))) -> Not Started
A22: M8. Infrastructure & Operations Merge | B22: =COUNTIF('Merge Plan'!$B$5:$B$87,$A22) -> 7 | C22: =COUNTIFS('Merge Plan'!$B$5:$B$87,$A22,'Merge Plan'!$I$5:$I$87,"Done") -> 0 | D22: =COUNTIFS('Merge Plan'!$B$5:$B$87,$A22,'Merge Plan'!$I$5:$I$87,"Blocked") -> 0 | E22: =_xlfn.MINIFS('Merge Plan'!$E$5:$E$87,'Merge Plan'!$B$5:$B$87,$A22) -> 46280 | F22: =_xlfn.MAXIFS('Merge Plan'!$F$5:$F$87,'Merge Plan'!$B$5:$B$87,$A22) -> 46295 | G22: =IFERROR(AVERAGEIF('Merge Plan'!$B$5:$B$87,$A22,'Merge Plan'!$J$5:$J$87),0) -> 0 | H22: =IF($D22>0,"Blocked",IF($C22=$B22,"Done",IF($C22>0,"In Progress","Not Started"))) -> Not Started
A23: M9. Phased Customer Migration (Pilot) | B23: =COUNTIF('Merge Plan'!$B$5:$B$87,$A23) -> 6 | C23: =COUNTIFS('Merge Plan'!$B$5:$B$87,$A23,'Merge Plan'!$I$5:$I$87,"Done") -> 0 | D23: =COUNTIFS('Merge Plan'!$B$5:$B$87,$A23,'Merge Plan'!$I$5:$I$87,"Blocked") -> 0 | E23: =_xlfn.MINIFS('Merge Plan'!$E$5:$E$87,'Merge Plan'!$B$5:$B$87,$A23) -> 46289 | F23: =_xlfn.MAXIFS('Merge Plan'!$F$5:$F$87,'Merge Plan'!$B$5:$B$87,$A23) -> 46296 | G23: =IFERROR(AVERAGEIF('Merge Plan'!$B$5:$B$87,$A23,'Merge Plan'!$J$5:$J$87),0) -> 0 | H23: =IF($D23>0,"Blocked",IF($C23=$B23,"Done",IF($C23>0,"In Progress","Not Started"))) -> Not Started
A24: M10. Decommission (planning only by 1 Oct) | B24: =COUNTIF('Merge Plan'!$B$5:$B$87,$A24) -> 4 | C24: =COUNTIFS('Merge Plan'!$B$5:$B$87,$A24,'Merge Plan'!$I$5:$I$87,"Done") -> 0 | D24: =COUNTIFS('Merge Plan'!$B$5:$B$87,$A24,'Merge Plan'!$I$5:$I$87,"Blocked") -> 0 | E24: =_xlfn.MINIFS('Merge Plan'!$E$5:$E$87,'Merge Plan'!$B$5:$B$87,$A24) -> 46294 | F24: =_xlfn.MAXIFS('Merge Plan'!$F$5:$F$87,'Merge Plan'!$B$5:$B$87,$A24) -> 46296 | G24: =IFERROR(AVERAGEIF('Merge Plan'!$B$5:$B$87,$A24,'Merge Plan'!$J$5:$J$87),0) -> 0 | H24: =IF($D24>0,"Blocked",IF($C24=$B24,"Done",IF($C24>0,"In Progress","Not Started"))) -> Not Started
A25: TOTAL | B25: =SUM(B13:B24) -> 83 | C25: =SUM(C13:C24) -> 0 | D25: =SUM(D13:D24) -> 0 | E25: =MIN(E13:E24) -> 46273 | F25: =MAX(F13:F24) -> 46296 | G25: =IFERROR(AVERAGE('Merge Plan'!$J$5:$J$87),0) -> 0

Sheet Legend & Assumptions
A1: How to use this workbook
A4: EDIT THESE COLUMNS on the 'Merge Plan' tab | B4: Owner, Start, End, Status, % Done - shown as blue text on a yellow fill.
A5: DO NOT EDIT | B5: Work Days is a NETWORKDAYS formula. The whole 'Milestone Summary' tab is formulas.
A6: Status values | B6: Not Started / In Progress / Blocked / Done / Deferred (dropdown on the Status column).
A7: Critical Path = Y | B7: Slipping this task slips the 1 Oct date. There are no spare days to absorb it.
A8: GATE in the Notes column | B8: A hard stop. Do not begin dependent work until that exit criterion is met.
A10: EXAMPLE ROW - this is the format expected in the editable columns
A11: ID | B11: Milestone | C11: Task | D11: Owner | E11: Start | F11: End | G11: Status | H11: % Done
A12: 1.4 | B12: M1. Discovery & Inventory | C12: List all auth methods, IdPs, token and session mechanisms | D12: A. Ben Salah | E12: 46274 | F12: 46275 | G12: In Progress | H12: 0.6
A14: Assumptions behind the dates
A15: - Start 8 Sep 2026 and deadline 1 Oct 2026 were both supplied by the user.
A16: - 18 working days are available in that window (weekends excluded, no public holidays assumed - adjust if Tunisian holidays apply).
A17: - This window is NOT enough to complete a full SaaS merge. Data migration and billing consolidation normally run for months.
A18: - The plan is therefore scoped to: discovery, architecture decision, identity unification, a tested and reconciled migration, and a PILOT cutover on 30 Sep.
A19: - The 1 Oct deliverable is milestone M9.6 - a go/no-go decision plus a signed wave schedule - not a fully migrated customer base.
A20: - Explicitly deferred past 1 Oct: full-fleet migration (4.10), complete design-system convergence (7.3), penetration testing (8.5), and legacy decommission (M10).
A21: - Owner names are role placeholders. Replace them with real people; one unnamed owner is the most common cause of slippage.
A22: - Task durations assume a dedicated team from both systems, not people fitting this around a normal roadmap.
A23: - Every milestone can be compressed except M4 (migration dry runs), M5.3 (legal notice periods) and M1b (defect stabilisation), which are bounded by reality rather than effort.
A24: - One of the two systems is reported as buggy (user-supplied). Milestone M1b was added for defect triage and data-integrity work, and the ETL mapping spec (4.1) now waits on data-quality profiling (1b.6).
A25: - M1b adds roughly a week of serial work in front of the migration. The pilot cutover on 30 Sep now has effectively zero float - see the Broken system guidance below.
... A39: The rule to hold onto: do not migrate data you cannot vouch for. Quarantining a bad record is recoverable. Silently importing it into the surviving system is not.
